README.txt
setup.py
cs/__init__.py
cs.pfg.xmlmailer.egg-info/PKG-INFO
cs.pfg.xmlmailer.egg-info/SOURCES.txt
cs.pfg.xmlmailer.egg-info/dependency_links.txt
cs.pfg.xmlmailer.egg-info/entry_points.txt
cs.pfg.xmlmailer.egg-info/namespace_packages.txt
cs.pfg.xmlmailer.egg-info/not-zip-safe
cs.pfg.xmlmailer.egg-info/paster_plugins.txt
cs.pfg.xmlmailer.egg-info/requires.txt
cs.pfg.xmlmailer.egg-info/top_level.txt
cs/pfg/__init__.py
cs/pfg/xmlmailer/__init__.py
cs/pfg/xmlmailer/config.py
cs/pfg/xmlmailer/configure.zcml
cs/pfg/xmlmailer/dummy.pt
cs/pfg/xmlmailer/mailadapter.py
cs/pfg/xmlmailer/rebuild_i18n.sh
cs/pfg/xmlmailer/tests.py
cs/pfg/xmlmailer/version.txt
cs/pfg/xmlmailer/Extensions/__init__.py
cs/pfg/xmlmailer/Extensions/install.py
cs/pfg/xmlmailer/locales/cs.pfg.xmlmailer-manual.pot
cs/pfg/xmlmailer/locales/cs.pfg.xmlmailer.pot
cs/pfg/xmlmailer/locales/es/LC_MESSAGES/cs.pfg.xmlmailer.mo
cs/pfg/xmlmailer/locales/es/LC_MESSAGES/cs.pfg.xmlmailer.po
cs/pfg/xmlmailer/locales/eu/LC_MESSAGES/cs.pfg.xmlmailer.mo
cs/pfg/xmlmailer/locales/eu/LC_MESSAGES/cs.pfg.xmlmailer.po
cs/pfg/xmlmailer/profiles/default/factorytool.xml
cs/pfg/xmlmailer/profiles/default/propertiestool.xml
cs/pfg/xmlmailer/profiles/default/rolemap.xml
cs/pfg/xmlmailer/profiles/default/types.xml
cs/pfg/xmlmailer/profiles/default/types/FormFolder.xml
cs/pfg/xmlmailer/profiles/default/types/XMLMailerAdapter.xml
docs/HISTORY.txt
docs/INSTALL.txt
docs/LICENSE.GPL
docs/LICENSE.txt