Metadata-Version: 1.1
Name: cs.pfg.xmlmailer
Version: 0.2
Summary: Send by e-mail an XML file representing the form data together with the e-mail
Home-page: http://svn.plone.org/svn/plone/plone.app.example
Author: Lur Ibargutxi
Author-email: libargutxi@codesyntax.com
License: GPL
Platform: UNKNOWN
Classifier: Framework :: Plone
Classifier: Programming Language :: Python
Classifier: Topic :: Software Development :: Libraries :: Python Modules
